odoo/addons/stock_picking_report_delivery_cost/README.rst
odoo/addons/stock_picking_report_delivery_cost/__init__.py
odoo/addons/stock_picking_report_delivery_cost/__manifest__.py
odoo/addons/stock_picking_report_delivery_cost/i18n/es.po
odoo/addons/stock_picking_report_delivery_cost/i18n/fr.po
odoo/addons/stock_picking_report_delivery_cost/i18n/it.po
odoo/addons/stock_picking_report_delivery_cost/i18n/stock_picking_report_delivery_cost.pot
odoo/addons/stock_picking_report_delivery_cost/models/__init__.py
odoo/addons/stock_picking_report_delivery_cost/models/stock_picking.py
odoo/addons/stock_picking_report_delivery_cost/readme/CONTRIBUTORS.md
odoo/addons/stock_picking_report_delivery_cost/readme/DESCRIPTION.md
odoo/addons/stock_picking_report_delivery_cost/readme/USAGE.md
odoo/addons/stock_picking_report_delivery_cost/report/report_deliveryslip.xml
odoo/addons/stock_picking_report_delivery_cost/report/report_shipping.xml
odoo/addons/stock_picking_report_delivery_cost/static/description/icon.png
odoo/addons/stock_picking_report_delivery_cost/static/description/index.html
odoo/addons/stock_picking_report_delivery_cost/tests/__init__.py
odoo/addons/stock_picking_report_delivery_cost/tests/test_stock_picking_report_delivery_cost.py
odoo_addon_stock_picking_report_delivery_cost-18.0.1.0.0.2.dist-info/METADATA
odoo_addon_stock_picking_report_delivery_cost-18.0.1.0.0.2.dist-info/WHEEL
odoo_addon_stock_picking_report_delivery_cost-18.0.1.0.0.2.dist-info/top_level.txt
odoo_addon_stock_picking_report_delivery_cost-18.0.1.0.0.2.dist-info/RECORD
